cedartl/__init__.py
cedartl/_version.py
cedartl/cedartl_processor.py
cedartl-0.1.1.dist-info/LICENSE
cedartl-0.1.1.dist-info/METADATA
cedartl-0.1.1.dist-info/WHEEL
cedartl-0.1.1.dist-info/top_level.txt
cedartl-0.1.1.dist-info/RECORD
