Metadata-Version: 2.1
Name: cedartl
Version: 0.1.1
Summary: A lightweight, intuitive templating language designed for interactive use in LLM chat sessions.
Author-email: Elifarley <cedarscript@orgecc.com>
License: Apache-2.0
Project-URL: Homepage, https://github.com/CedarVerse/cedartl
Project-URL: Documentation, https://github.com/CedarVerse/cedartl#readme
Project-URL: Repository, https://github.com/CedarVerse/cedartl.git
Project-URL: Bug Tracker, https://github.com/CedarVerse/cedartl/issues
Project-URL: Change Log, https://github.com/CedarVerse/cedartl/blob/main/CHANGELOG.md
Keywords: llm,templating,productivity,ai-development,code-generation,prompt-engineering,prompt-management,language-processing,development-tools
Classifier: Development Status :: 4 - Beta
Classifier: Intended Audience :: Developers
Classifier: License :: OSI Approved :: Apache Software License
Classifier: Operating System :: OS Independent
Classifier: Programming Language :: Python :: 3
Classifier: Programming Language :: Python :: 3.11
Classifier: Programming Language :: Python :: 3.12
Classifier: Topic :: Software Development :: Libraries :: Python Modules
Classifier: Topic :: Software Development :: Code Generators
Classifier: Topic :: Text Processing :: General
Classifier: Topic :: Software Development :: Libraries :: Application Frameworks
Classifier: Typing :: Typed
Requires-Python: >=3.11
License-File: LICENSE
Provides-Extra: dev
Requires-Dist: pytest>=7.0; extra == "dev"
Requires-Dist: black>=22.0; extra == "dev"
Requires-Dist: ruff>=0.1.0; extra == "dev"
Requires-Dist: mypy>=0.900; extra == "dev"
Requires-Dist: coverage>=6.0; extra == "dev"
Requires-Dist: tox>=3.24; extra == "dev"
Provides-Extra: docs
Requires-Dist: sphinx>=7.0; extra == "docs"
Requires-Dist: sphinx-rtd-theme>=1.3; extra == "docs"
Requires-Dist: myst-parser>=2.0; extra == "docs"
